delicatessen/__init__.py
delicatessen/data.py
delicatessen/derivative.py
delicatessen/errors.py
delicatessen/estimation.py
delicatessen/helper.py
delicatessen/sandwich.py
delicatessen/utilities.py
delicatessen/version.py
delicatessen/estimating_equations/__init__.py
delicatessen/estimating_equations/basic.py
delicatessen/estimating_equations/causal.py
delicatessen/estimating_equations/measurement.py
delicatessen/estimating_equations/pharmacokinetics.py
delicatessen/estimating_equations/processing.py
delicatessen/estimating_equations/regression.py
delicatessen/estimating_equations/survival.py
delicatessen-4.0.dist-info/licenses/LICENSE
delicatessen-4.0.dist-info/METADATA
delicatessen-4.0.dist-info/WHEEL
delicatessen-4.0.dist-info/top_level.txt
delicatessen-4.0.dist-info/RECORD
