Metadata-Version: 2.4
Name: delicatessen
Version: 4.0
Summary: Generalized M-Estimation
Home-page: https://github.com/pzivich/Deli
Author: Paul Zivich
Author-email: zivich.5@gmail.com
License: MIT
Keywords: m-estimation sandwich-variance estimating-equations
Classifier: Programming Language :: Python :: 3.8
Classifier: Programming Language :: Python :: 3.9
Classifier: Programming Language :: Python :: 3.10
Classifier: Programming Language :: Python :: 3.11
Classifier: Programming Language :: Python :: 3.12
Classifier: Programming Language :: Python :: 3.13
Classifier: Programming Language :: Python :: 3.14
License-File: LICENSE
Requires-Dist: numpy>=1.18.5
Requires-Dist: scipy>=1.9.0
Dynamic: author
Dynamic: author-email
Dynamic: classifier
Dynamic: description
Dynamic: description-content-type
Dynamic: home-page
Dynamic: keywords
Dynamic: license
Dynamic: license-file
Dynamic: requires-dist
Dynamic: summary
